README.md
setup.py
tegrity/__init__.py
tegrity/__main__.py
tegrity/_apt_firstboot_dpkg.py
tegrity/apt.py
tegrity/cli.py
tegrity/db.py
tegrity/download.py
tegrity/err.py
tegrity/firstboot.py
tegrity/gui.py
tegrity/image.py
tegrity/kernel.py
tegrity/qemu.py
tegrity/rootfs.py
tegrity/service.py
tegrity/settings.py
tegrity/tegrity-firstboot.service.in
tegrity/tegrity-firstboot.service.in.LICENSE.txt
tegrity/tegrity-service-simple.service.in
tegrity/toolchain.py
tegrity/utils.py
tegrity.egg-info/PKG-INFO
tegrity.egg-info/SOURCES.txt
tegrity.egg-info/dependency_links.txt
tegrity.egg-info/entry_points.txt
tegrity.egg-info/top_level.txt