Metadata-Version: 2.1
Name: tegrity
Version: 0.0.3
Summary: Helps bake system images for NVIDIA Tegra
Home-page: UNKNOWN
Author: Michael de Gans
Author-email: michael.john.degans@gmail.com
License: UNKNOWN
Project-URL: Bug Reports, https://github.com/mdegans/tegrity/issues
Project-URL: Source, https://github.com/mdegans/tegrity/
Platform: UNKNOWN
Classifier: Development Status :: 3 - Alpha
Classifier: Intended Audience :: Developers
Classifier: Topic :: Software Development :: Build Tools
Classifier: License :: OSI Approved :: MIT License
Classifier: Programming Language :: Python :: 3
Classifier: Programming Language :: Python :: 3.6
Classifier: Programming Language :: Python :: 3.7
Classifier: Programming Language :: Python :: 3.8
Requires-Python: >=3.6
